vlsim/__init__.py
vlsim/__main__.py
vlsim/vl_options.py
vlsim/templates/vlsim.mk
vlsim/templates/vlsim_main.cpp
vlsim/tsr/__init__.py
vlsim/tsr/vlsim_tsr_plugin.py
vlsim-0.0.2.1387798432.dist-info/LICENSE
vlsim-0.0.2.1387798432.dist-info/METADATA
vlsim-0.0.2.1387798432.dist-info/WHEEL
vlsim-0.0.2.1387798432.dist-info/entry_points.txt
vlsim-0.0.2.1387798432.dist-info/top_level.txt
vlsim-0.0.2.1387798432.dist-info/RECORD
